pygjx/__init__.py
pygjx-1.0.2.dist-info/METADATA
pygjx-1.0.2.dist-info/WHEEL
pygjx-1.0.2.dist-info/top_level.txt
pygjx-1.0.2.dist-info/RECORD
